h2tinker/__init__.py
h2tinker/assrt.py
h2tinker/frames.py
h2tinker/h2_connection.py
h2tinker/h2_plain_connection.py
h2tinker/h2_tls_connection.py
h2tinker/log.py
h2tinker-0.3.dist-info/LICENSE
h2tinker-0.3.dist-info/METADATA
h2tinker-0.3.dist-info/WHEEL
h2tinker-0.3.dist-info/top_level.txt
h2tinker-0.3.dist-info/RECORD
