Metadata-Version: 2.1
Name: h2tinker
Version: 0.3
Summary: Low-level HTTP/2 client library based on scapy for tinkering with HTTP/2 connections
Home-page: https://github.com/kspar/h2tinker
Author: Kaspar Papli
Author-email: kaspar.papli@gmail.com
License: UNKNOWN
Platform: UNKNOWN
Classifier: Programming Language :: Python :: 3
Classifier: License :: OSI Approved :: MIT License
Classifier: Operating System :: OS Independent
Requires-Python: >=3.6
Requires-Dist: scapy (==2.4.3)
